authlibps/__init__.py
authlibps/constants.py
authlibps/helpers.py
authlib_provider_support-0.0.2.dist-info/LICENSE.txt
authlib_provider_support-0.0.2.dist-info/METADATA
authlib_provider_support-0.0.2.dist-info/WHEEL
authlib_provider_support-0.0.2.dist-info/RECORD
