Metadata-Version: 2.1
Name: authlib-provider-support
Version: 0.0.2
Summary: AuthLib Provider Support Package
License: LICENSE.txt
Keywords: python
Author: Myron Walker
Requires-Python: >=3.9,<4.0
Classifier: License :: OSI Approved :: MIT License
Classifier: License :: Other/Proprietary License
Classifier: Operating System :: POSIX
Classifier: Programming Language :: Python :: 3
Classifier: Programming Language :: Python :: 3.9
Classifier: Programming Language :: Python :: 3.10
Classifier: Programming Language :: Python :: 3.11
Classifier: Programming Language :: Python :: 3.12
